largestinteriorrectangle/__init__.py
largestinteriorrectangle/lir.py
largestinteriorrectangle/lir_basis.py
largestinteriorrectangle/lir_within_contour.py
largestinteriorrectangle/lir_within_polygon.py
largestinteriorrectangle-0.2.1.dist-info/LICENSE
largestinteriorrectangle-0.2.1.dist-info/METADATA
largestinteriorrectangle-0.2.1.dist-info/WHEEL
largestinteriorrectangle-0.2.1.dist-info/top_level.txt
largestinteriorrectangle-0.2.1.dist-info/RECORD
