Metadata-Version: 2.1
Name: largestinteriorrectangle
Version: 0.2.1
Summary: Fast Largest Interior Rectangle calculation
Author: Lukas Weber
Author-email: l.a.weber@outlook.de
License: Apache License 2.0
Project-URL: Source, https://github.com/lukasalexanderweber/lir
Project-URL: Bug Tracker, https://github.com/lukasalexanderweber/lir/issues
Platform: any
Classifier: Programming Language :: Python :: 3 :: Only
License-File: LICENSE
Requires-Dist: numba
